okta_jwt_verifier/__init__.py
okta_jwt_verifier/config_validator.py
okta_jwt_verifier/constants.py
okta_jwt_verifier/error_messages.py
okta_jwt_verifier/exceptions.py
okta_jwt_verifier/jwt_utils.py
okta_jwt_verifier/jwt_verifier.py
okta_jwt_verifier/request_executor.py
okta_jwt_verifier-0.4.0.dist-info/LICENSE.md
okta_jwt_verifier-0.4.0.dist-info/METADATA
okta_jwt_verifier-0.4.0.dist-info/WHEEL
okta_jwt_verifier-0.4.0.dist-info/RECORD
