Metadata-Version: 2.3
Name: okta-jwt-verifier
Version: 0.4.0
Summary: A Python library for OKTA JWT tokens validation
License: Apache-2.0
Author: Okta
Requires-Python: >=3.8,<4.0
Classifier: License :: OSI Approved :: Apache Software License
Classifier: Programming Language :: Python :: 3
Classifier: Programming Language :: Python :: 3.8
Classifier: Programming Language :: Python :: 3.9
Classifier: Programming Language :: Python :: 3.10
Classifier: Programming Language :: Python :: 3.11
Classifier: Programming Language :: Python :: 3.12
Classifier: Programming Language :: Python :: 3.13
Requires-Dist: PyJWT (>=2.8.0,<3.0.0)
Requires-Dist: acachecontrol (>=0.3.6,<0.4.0)
Requires-Dist: retry2 (>=0.9.5,<0.10.0)
